manuscriptify/__main__.py
manuscriptify/bin.py
manuscriptify/chapter.py
manuscriptify/constants.py
manuscriptify/exceptions.py
manuscriptify/filetree.py
manuscriptify/formatter.py
manuscriptify/fragment.py
manuscriptify/functions.py
manuscriptify/manuscript.py
manuscriptify/parser.py
manuscriptify/google_api/auth.py
manuscriptify/google_api/clients.py
manuscriptify/google_api/manuscriptify.py
manuscriptify-1.2.2.dist-info/METADATA
manuscriptify-1.2.2.dist-info/WHEEL
manuscriptify-1.2.2.dist-info/entry_points.txt
manuscriptify-1.2.2.dist-info/top_level.txt
manuscriptify-1.2.2.dist-info/RECORD
