Metadata-Version: 2.1
Name: manuscriptify
Version: 1.2.2
Summary: Compile google docs into a manuscript
Home-page: https://manuscriptify.com
Author: Jonas McCallum
Author-email: jonasmccallum@gmail.com
Project-URL: README, https://manuscriptify.com/free-4ab6b87c95a5
Requires-Dist: google-api-python-client
Requires-Dist: google-auth-oauthlib
Requires-Dist: pyyaml
Provides-Extra: testing
Requires-Dist: pytest ; extra == 'testing'
